bb_logger/__init__.py
bb_logger/constant.py
bb_logger/logger.py
bb_logger/slack.py
bb_logger-0.3.3.dist-info/LICENSE.txt
bb_logger-0.3.3.dist-info/METADATA
bb_logger-0.3.3.dist-info/WHEEL
bb_logger-0.3.3.dist-info/top_level.txt
bb_logger-0.3.3.dist-info/RECORD
