Metadata-Version: 2.1
Name: bb-logger
Version: 0.3.3
Summary: setup logger bb
Home-page: https://github.com/dulx96/bb_logger.git
Author: le du
Author-email: dulx96@gmail.com
License: MIT
Keywords: BB,LOGGER,LOGGING
Platform: UNKNOWN
Classifier: Development Status :: 3 - Alpha
Classifier: Intended Audience :: Developers
Classifier: Topic :: Software Development :: Build Tools
Classifier: License :: OSI Approved :: MIT License
Classifier: Programming Language :: Python :: 3
Requires-Dist: slack-sdk (>=3.5.1)
